MANIFEST.in
README.md
setup.py
dash_react_table/DashReactTable.py
dash_react_table/__init__.py
dash_react_table/_imports_.py
dash_react_table/dash_react_table.dev.js
dash_react_table/dash_react_table.min.js
dash_react_table/metadata.json
dash_react_table/package.json
dash_react_table.egg-info/PKG-INFO
dash_react_table.egg-info/SOURCES.txt
dash_react_table.egg-info/dependency_links.txt
dash_react_table.egg-info/requires.txt
dash_react_table.egg-info/top_level.txt