Metadata-Version: 1.0
Name: dash-react-table
Version: 0.0.2
Summary: Dash component for React-Table
Home-page: UNKNOWN
Author: Maxim Kupfer <mbkupfer@gmail.com>
Author-email: UNKNOWN
License: MIT
Platform: UNKNOWN
